README.md
setup.py
improved_ArXiv.egg-info/PKG-INFO
improved_ArXiv.egg-info/SOURCES.txt
improved_ArXiv.egg-info/dependency_links.txt
improved_ArXiv.egg-info/not-zip-safe
improved_ArXiv.egg-info/top_level.txt
improved_arxiv/__init__.py
improved_arxiv/pyArXiv.py