Metadata-Version: 1.0
Name: improved-ArXiv
Version: 0.0.2
Summary: ArXiv paper downloader
Home-page: https://github.com/devArtoria/pyArXiv
Author: Lewis Kim
Author-email: artoria@istruly.sexy
License: bbakbbak2
Keywords: ArXiv,parsing,downloader
Platform: UNKNOWN
